setup.py
txque/__init__.py
txque/functools.py
txque/work.py
txque.egg-info/PKG-INFO
txque.egg-info/SOURCES.txt
txque.egg-info/dependency_links.txt
txque.egg-info/requires.txt
txque.egg-info/top_level.txt
txque/dispatchers/__init__.py
txque/dispatchers/sql.py