Metadata-Version: 1.1
Name: txque
Version: 0.1
Summary: txque is a Python library for running asynchronous jobs using Twisted.
Home-page: http://github.com/bmuller/txque
Author: Brian Muller
Author-email: bamuller@gmail.com
License: MIT
Platform: UNKNOWN
Requires: twisted
Requires: twistar
